{
  "indexes": [
    {
      "collectionGroup": "events",
      "queryScope": "COLLECTION",
      "fields": [
        {
          "fieldPath": "status",
          "order": "ASCENDING"
        },
        {
          "fieldPath": "type",
          "order": "ASCENDING"
        },
        {
          "fieldPath": "createdAt",
          "order": "DESCENDING"
        }
      ]
    },
    {
      "collectionGroup": "events",
      "queryScope": "COLLECTION",
      "fields": [
        {
          "fieldPath": "status",
          "order": "ASCENDING"
        },
        {
          "fieldPath": "dateStart",
          "order": "ASCENDING"
        }
      ]
    },
    {
      "collectionGroup": "events",
      "queryScope": "COLLECTION",
      "fields": [
        {
          "fieldPath": "creatorId",
          "order": "ASCENDING"
        },
        {
          "fieldPath": "status",
          "order": "ASCENDING"
        },
        {
          "fieldPath": "createdAt",
          "order": "DESCENDING"
        }
      ]
    },
    {
      "collectionGroup": "events",
      "queryScope": "COLLECTION",
      "fields": [
        {
          "fieldPath": "tags",
          "arrayConfig": "CONTAINS"
        },
        {
          "fieldPath": "status",
          "order": "ASCENDING"
        },
        {
          "fieldPath": "createdAt",
          "order": "DESCENDING"
        }
      ]
    },
    {
      "collectionGroup": "events",
      "queryScope": "COLLECTION",
      "fields": [
        {
          "fieldPath": "location.city",
          "order": "ASCENDING"
        },
        {
          "fieldPath": "status",
          "order": "ASCENDING"
        },
        {
          "fieldPath": "createdAt",
          "order": "DESCENDING"
        }
      ]
    },
    {
      "collectionGroup": "bookings",
      "queryScope": "COLLECTION",
      "fields": [
        {
          "fieldPath": "userId",
          "order": "ASCENDING"
        },
        {
          "fieldPath": "status",
          "order": "ASCENDING"
        },
        {
          "fieldPath": "createdAt",
          "order": "DESCENDING"
        }
      ]
    },
    {
      "collectionGroup": "bookings",
      "queryScope": "COLLECTION",
      "fields": [
        {
          "fieldPath": "eventId",
          "order": "ASCENDING"
        },
        {
          "fieldPath": "status",
          "order": "ASCENDING"
        },
        {
          "fieldPath": "date",
          "order": "ASCENDING"
        }
      ]
    },
    {
      "collectionGroup": "chat_sessions",
      "queryScope": "COLLECTION",
      "fields": [
        {
          "fieldPath": "userId",
          "order": "ASCENDING"
        },
        {
          "fieldPath": "status",
          "order": "ASCENDING"
        },
        {
          "fieldPath": "updatedAt",
          "order": "DESCENDING"
        }
      ]
    },
    {
      "collectionGroup": "packages",
      "queryScope": "COLLECTION",
      "fields": [
        {
          "fieldPath": "eventTypes",
          "arrayConfig": "CONTAINS"
        },
        {
          "fieldPath": "priceRange.min",
          "order": "ASCENDING"
        }
      ]
    },
    {
      "collectionGroup": "analytics_events",
      "queryScope": "COLLECTION",
      "fields": [
        {
          "fieldPath": "eventType",
          "order": "ASCENDING"
        },
        {
          "fieldPath": "timestamp",
          "order": "DESCENDING"
        }
      ]
    },
    {
      "collectionGroup": "analytics_events",
      "queryScope": "COLLECTION",
      "fields": [
        {
          "fieldPath": "userId",
          "order": "ASCENDING"
        },
        {
          "fieldPath": "timestamp",
          "order": "DESCENDING"
        }
      ]
    }
  ],
  "fieldOverrides": [
    {
      "collectionGroup": "events",
      "fieldPath": "tags",
      "indexes": [
        {
          "order": "ASCENDING",
          "queryScope": "COLLECTION"
        },
        {
          "arrayConfig": "CONTAINS",
          "queryScope": "COLLECTION"
        }
      ]
    },
    {
      "collectionGroup": "packages",
      "fieldPath": "eventTypes",
      "indexes": [
        {
          "order": "ASCENDING",
          "queryScope": "COLLECTION"
        },
        {
          "arrayConfig": "CONTAINS",
          "queryScope": "COLLECTION"
        }
      ]
    }
  ]
}
